{"cameraMode":{"drawMode":0,"name":"Shaded","section":"Shading Mode"},"sceneLighting":false,"audioPlay":false,"sceneViewState":{"m_AlwaysRefresh":false,"showFog":true,"showSkybox":false,"showFlares":true,"showImageEffects":true,"showParticleSystems":true,"showVisualEffectGraphs":true,"m_FxEnabled":true},"in2DMode":false,"pivot":{"x":3.0224061012268068,"y":-3.761951208114624,"z":2.855557918548584},"rotation":{"x":0.28530368208885195,"y":0.6084232330322266,"z":-0.24978850781917573,"w":0.6975858211517334},"size":4.44100284576416,"orthographic":false}