{"cameraMode":{"drawMode":0,"name":"Shaded","section":"Shading Mode"},"sceneLighting":false,"audioPlay":false,"sceneViewState":{"m_AlwaysRefresh":false,"showFog":true,"showSkybox":false,"showFlares":true,"showImageEffects":true,"showParticleSystems":true,"showVisualEffectGraphs":true,"m_FxEnabled":true},"in2DMode":false,"pivot":{"x":-2.540940284729004,"y":-1.5055960416793824,"z":0.5551842451095581},"rotation":{"x":0.12678487598896027,"y":-0.6534662842750549,"z":0.11178655922412873,"w":0.7381049394607544},"size":4.446346759796143,"orthographic":false}